odoo/addons/web_widget_numeric_step/README.rst
odoo/addons/web_widget_numeric_step/__init__.py
odoo/addons/web_widget_numeric_step/__manifest__.py
odoo/addons/web_widget_numeric_step/demo/ir_cron.xml
odoo/addons/web_widget_numeric_step/i18n/de.po
odoo/addons/web_widget_numeric_step/i18n/es.po
odoo/addons/web_widget_numeric_step/i18n/fr.po
odoo/addons/web_widget_numeric_step/i18n/it.po
odoo/addons/web_widget_numeric_step/i18n/web_widget_numeric_step.pot
odoo/addons/web_widget_numeric_step/readme/CONTRIBUTORS.md
odoo/addons/web_widget_numeric_step/readme/DESCRIPTION.md
odoo/addons/web_widget_numeric_step/readme/ROADMAP.md
odoo/addons/web_widget_numeric_step/readme/USAGE.md
odoo/addons/web_widget_numeric_step/static/description/add_two_buttons.png
odoo/addons/web_widget_numeric_step/static/description/icon.png
odoo/addons/web_widget_numeric_step/static/description/index.html
"odoo/addons/web_widget_numeric_step/static/description/step0,25andlimits.gif"
odoo/addons/web_widget_numeric_step/static/description/step10_limit15_placeholder117_with_onchange.gif
odoo/addons/web_widget_numeric_step/static/src/numeric_step.esm.js
odoo/addons/web_widget_numeric_step/static/src/numeric_step.scss
odoo/addons/web_widget_numeric_step/static/src/numeric_step.xml
odoo_addon_web_widget_numeric_step-18.0.1.0.2.dist-info/METADATA
odoo_addon_web_widget_numeric_step-18.0.1.0.2.dist-info/WHEEL
odoo_addon_web_widget_numeric_step-18.0.1.0.2.dist-info/top_level.txt
odoo_addon_web_widget_numeric_step-18.0.1.0.2.dist-info/RECORD
